knave/__init__.py
knave/acl.py
knave/identity.py
knave/middleware.py
knave/predicates.py
knave/roles.py
knave-1.0.0.dist-info/DESCRIPTION.rst
knave-1.0.0.dist-info/METADATA
knave-1.0.0.dist-info/RECORD
knave-1.0.0.dist-info/WHEEL
knave-1.0.0.dist-info/metadata.json
knave-1.0.0.dist-info/top_level.txt
