Metadata-Version: 2.0
Name: knave
Version: 1.0.0
Summary: Authorization for web apps: permissions, groups, roles, ACLs
Home-page: https://ollycope.com/software/knave/latest/
Author: Oliver Cope
Author-email: oliver@redgecko.org
License: Apache
Keywords: authorization,authorisation authentication security permissions roles groups wsgi acl
Platform: UNKNOWN
Classifier: Development Status :: 5 - Production/Stable
Classifier: Environment :: Web Environment
Classifier: Intended Audience :: Developers
Classifier: License :: OSI Approved :: Apache Software License
Classifier: Operating System :: OS Independent
Classifier: Topic :: Internet :: WWW/HTTP :: WSGI
Classifier: Programming Language :: Python :: 3
